{
    "maintainers": [
        {
            "name": "Volker Krause",
            "github": "vkrause"
        },
        {
            "name": "Jonah Brüchert",
            "github": "jbruechert"
        }
    ],
    "sources": [
        {
            "name": "fintraffic",
            "type": "http",
            "url": "https://mobility.mobility-database.fintraffic.fi/static/finland_gtfs.zip",
            "license": {
                "spdx-identifier": "CC-BY-4.0",
                "url": "https://www.fintraffic.fi/fi/digitaalisetpalvelut/fintrafficin-datapalvelut/liikkumisen-tietopalvelut/joukkoliikenteen-tietopalvelut/koontipalvelu"
            },
            "fix": true,
            "drop-agency-names": [
                "FlixBus-eu",
                "FlixTrain-eu",
                "VR",
                "Pohjois-Suomen Rautatieharrastajat ry",
                "Sinisten vaunujen ystävät ry"
            ],
            "default-timezone": "Europe/Helsinki"
        },
        {
            "name": "digitraffic",
            "type": "http",
            "url": "https://rata.digitraffic.fi/api/v1/trains/gtfs-all.zip",
            "license": {
                "spdx-identifier": "CC-BY-4.0",
                "url": "https://www.digitraffic.fi/en/railway-traffic/"
            },
            "fix": true,
            "http-options": {
                "headers": {
                    "accept-encoding": "gzip"
                }
            }
        },
        {
            "name": "digitraffic",
            "type": "url",
            "spec": "gtfs-rt",
            "url": "https://rata.digitraffic.fi/api/v1/trains/gtfs-rt-updates",
            "license": {
                "spdx-identifier": "CC-BY-4.0",
                "url": "https://www.digitraffic.fi/en/railway-traffic/"
            }
        },
        {
            "name": "229",
            "type": "transitland-atlas",
            "transitland-atlas-id": "f-ued-oulunjoukkoliikenne"
        },
        {
            "name": "hsl",
            "type": "transitland-atlas",
            "transitland-atlas-id": "f-ud9-helsinginseudunliikenne"
        },
        {
            "name": "hsl",
            "spec": "gtfs-rt",
            "type": "url",
            "url": "https://realtime.hsl.fi/realtime/service-alerts/v2/hsl"
        }
    ]
}
