{
    "maintainers": [
        {
            "name": "Petr Novak",
            "github": "hoermalmeister"
        },
        {
            "name": "Nedžad Beus",
            "github": "vekejsn"
        }
    ],
    "sources": [
        {
            "name": "zr-north-macedonia",
            "type": "http",
            "url": "https://owncloud.cesnet.cz/index.php/s/v3QvHCm2JtOnF6e/download"
        },
        {
            "name": "jsp",
            "type": "http",
            "url": "https://www.modeshift.app/api/v1/9814b106-2afe-47c8-919b-bdec6a5e521e/transport/gtfs/gtfs.zip"
        },
        {
            "name": "jsp",
            "type": "url",
            "spec": "gtfs-rt",
            "url": "https://www.modeshift.app/api/v1/9814b106-2afe-47c8-919b-bdec6a5e521e/transport/gtfsrt/tripupdates.pb"
        },
        {
            "name": "jsp",
            "type": "url",
            "spec": "gtfs-rt",
            "url": "https://www.modeshift.app/api/v1/9814b106-2afe-47c8-919b-bdec6a5e521e/transport/gtfsrt/alerts.pb"
        }
      ]
}
