{
    "maintainers": [
        {
            "name": "Marcus Lundblad",
            "github": "mlundblad"
        }
    ],
    "sources": [
        {
            "name": "WMATA-bus",
            "type": "transitland-atlas",
            "transitland-atlas-id": "f-dqc-wmata~bus",
            "api-key": "805c9dcd1a43482597e501957f5b1d31"
        },
        {
            "name": "WMATA-bus",
            "type": "transitland-atlas",
            "transitland-atlas-id": "f-wmata~bus~rt",
            "api-key": "805c9dcd1a43482597e501957f5b1d31"
        },
        {
            "name": "WMATA-rail",
            "type": "transitland-atlas",
            "transitland-atlas-id": "f-dqc-wmata~rail",
            "api-key": "805c9dcd1a43482597e501957f5b1d31"
        },
        {
            "name": "WMATA-rail",
            "type": "transitland-atlas",
            "transitland-atlas-id": "f-wmata~rail~rt",
            "api-key": "805c9dcd1a43482597e501957f5b1d31"
        }
    ]
}
